python3_captchaai/__init__.py
python3_captchaai/__version__.py
python3_captchaai/config.py
python3_captchaai/control.py
python3_captchaai/datadome_slider.py
python3_captchaai/enums.py
python3_captchaai/fun_captcha.py
python3_captchaai/gee_test.py
python3_captchaai/hcaptcha.py
python3_captchaai/image_to_text.py
python3_captchaai/kasada.py
python3_captchaai/mt_captcha.py
python3_captchaai/recaptcha.py
python3_captchaai/__pycache__/__init__.cpython-310.pyc
python3_captchaai/__pycache__/recaptcha.cpython-310.pyc
python3_captchaai-0.5.2.dist-info/METADATA
python3_captchaai-0.5.2.dist-info/WHEEL
python3_captchaai-0.5.2.dist-info/top_level.txt
python3_captchaai-0.5.2.dist-info/RECORD
