Metadata-Version: 2.1
Name: python3-captchaai
Version: 0.5.2
Summary: Python 3.7+ Capsolver library with AIO module.
Home-page: https://andreidrang.github.io/python3-captchaai/
Author: AndreiDrang
Author-email: python-captcha@pm.me
License: MIT
Project-URL: Documentation, https://andreidrang.github.io/python3-captchaai/
Project-URL: Source, https://github.com/AndreiDrang/python3-captchaai
Keywords: captcha
Classifier: License :: OSI Approved :: MIT License
Classifier: License :: OSI Approved :: Mozilla Public License 2.0 (MPL 2.0)
Classifier: Development Status :: 5 - Production/Stable
Classifier: Programming Language :: Python
Classifier: Programming Language :: Python :: 3
Classifier: Programming Language :: Python :: 3 :: Only
Classifier: Programming Language :: Python :: 3.7
Classifier: Programming Language :: Python :: 3.8
Classifier: Programming Language :: Python :: 3.9
Classifier: Programming Language :: Python :: 3.10
Classifier: Framework :: AsyncIO
Classifier: Operating System :: Unix
Classifier: Operating System :: Microsoft :: Windows
Classifier: Operating System :: MacOS
Requires-Python: >=3.7.0
Requires-Dist: requests (>=2.21.0)
Requires-Dist: aiohttp (>=3.7.4)
Requires-Dist: pydantic (==1.*)
Requires-Dist: tenacity (==8.*)
